wm_ssh/__init__.py
wm_ssh/cli.py
wm_ssh-0.4.1.dist-info/entry_points.txt
wm_ssh-0.4.1.dist-info/METADATA
wm_ssh-0.4.1.dist-info/LICENSE
wm_ssh-0.4.1.dist-info/WHEEL
wm_ssh-0.4.1.dist-info/RECORD
