Metadata-Version: 2.1
Name: wm-ssh
Version: 0.4.1
Summary: Wikimedia ssh wrapper to expand host names
Home-page: https://github.com/david-caro/wm-ssh
License: GPL-3.0-or-later
Author: David Caro
Author-email: me@dcaro.es
Requires-Python: >=3.8.1,<4.0
Classifier: License :: OSI Approved :: GNU General Public License v3 or later (GPLv3+)
Classifier: Programming Language :: Python :: 3
Classifier: Programming Language :: Python :: 3.9
Classifier: Programming Language :: Python :: 3.10
Classifier: Programming Language :: Python :: 3.11
Classifier: Topic :: Software Development :: Build Tools
Classifier: Topic :: Software Development :: Libraries
Classifier: Topic :: Software Development :: Libraries :: Python Modules
Requires-Dist: click (>=8.0.3,<9.0.0)
Requires-Dist: requests (>=2.27.1,<3.0.0)
Project-URL: Repository, https://github.com/david-caro/wm-ssh
